numprimo/__init__.py
numprimodeprueba-1.0.dist-info/LICENSE
numprimodeprueba-1.0.dist-info/METADATA
numprimodeprueba-1.0.dist-info/WHEEL
numprimodeprueba-1.0.dist-info/top_level.txt
numprimodeprueba-1.0.dist-info/RECORD
